hyload/__init__.py
hyload/httpclient.py
hyload/kill_hyload_worker.sh
hyload/logger.py
hyload/product.py
hyload/stats.py
hyload/util.py
hyload/tools/__init__.py
hyload/tools/plotperf.py
hyload/tools/plotresource.py
hyload/tools/remoteop.py
hyload/tools/statshub.py
hyload-0.5.0.dist-info/licenses/LICENSE.txt
hyload-0.5.0.dist-info/METADATA
hyload-0.5.0.dist-info/WHEEL
hyload-0.5.0.dist-info/top_level.txt
hyload-0.5.0.dist-info/RECORD
