Metadata-Version: 2.4
Name: hyload
Version: 0.5.0
Summary: load testing library
Author-email: Jiang Chunyang 白月黑羽-江春阳 <jcyrss@gmail.com>
License-Expression: MIT
Project-URL: Homepage, https://github.com/jcyrss/hyload
Project-URL: Download, https://pypi.python.org/pypi/hyload
Keywords: hyload,loadtesting
Classifier: Development Status :: 4 - Beta
Classifier: Intended Audience :: Developers
Classifier: Topic :: Software Development :: Testing
Requires-Python: >=3.8
License-File: LICENSE.txt
Requires-Dist: gevent>=22.10.2
Requires-Dist: matplotlib
Requires-Dist: paramiko>=3.2.0
Requires-Dist: websockets>=11.0.3
Dynamic: license-file
